<?xml version="1.0"?>
<qmcsystem>
  <wavefunction name="psi0" target="e">
    <determinantset type="MolecularOrbital" name="LCAOBSet" source="ion0" transform="yes" cuspCorrection="yes" href="Li_wopos.h5">
      <slaterdeterminant>
        <determinant id="updet" size="2" cuspInfo="../updet.cuspInfo.xml">
          <occupation mode="ground"/>
          <coefficient size="16" spindataset="0"/>
        </determinant>
        <determinant id="downdet" size="2" cuspInfo="../downdet.cuspInfo.xml">
          <occupation mode="ground"/>
          <coefficient size="16" spindataset="0"/>
        </determinant>
      </slaterdeterminant>
    </determinantset>
    <jastrow name="J2" type="Two-Body" function="Bspline" print="yes">
      <correlation rcut="10" size="10" speciesA="u" speciesB="u">
        <coefficients id="uu" type="Array"> 0.02055523304 -0.02478737148 -0.04190994278 -0.07768343444 -0.08159633085 -0.08490045047 -0.07529515755 -0.07628726223 -0.06320665064 -0.04236199773</coefficients>
      </correlation>
      <correlation rcut="10" size="10" speciesA="u" speciesB="d">
        <coefficients id="ud" type="Array"> 0.5084612411 0.264394805 0.1540734152 0.1042317115 0.0363553827 -0.01155688815 -0.05078116776 -0.08198480156 -0.07772071542 -0.0610729035</coefficients>
      </correlation>
    </jastrow>
    <jastrow name="J1" type="One-Body" function="Bspline" source="ion0" print="yes">
      <correlation rcut="10" size="10" cusp="0" elementType="Li">
        <coefficients id="eLi" type="Array"> -0.4040386439 -0.1505819271 -0.1952643049 -0.08190520186 -0.07255031796 -0.05594481941 -0.04499840528 -0.02295141951 0.002165812366 0.02242482785</coefficients>
      </correlation>
    </jastrow>
  </wavefunction>
</qmcsystem>
